text2clusters/__init__.py
text2clusters/cli.py
text2clusters/clustering.py
text2clusters/embedding.py
text2clusters/pipeline.py
text2clusters/reduction.py
text2clusters/reporting.py
text2clusters-0.1.3.dist-info/METADATA
text2clusters-0.1.3.dist-info/WHEEL
text2clusters-0.1.3.dist-info/entry_points.txt
text2clusters-0.1.3.dist-info/licenses/LICENSE
text2clusters-0.1.3.dist-info/RECORD
