Metadata-Version: 2.4
Name: text2clusters
Version: 0.1.3
Summary: Text clustering with embeddings, PCA, DBSCAN/KMeans, and reporting.
Project-URL: Homepage, https://github.com/self-ms/text2clusters
Project-URL: Repository, https://github.com/self-ms/text2clusters.git
Project-URL: Issues, https://github.com/self-ms/text2clusters/issues
Project-URL: Changelog, https://github.com/self-ms/text2clusters/releases
Author-email: mohammd salehi <sefl.mohammd.salehi@gmail.com>
License: MIT
License-File: LICENSE
Keywords: clustering,dbscan,embeddings,nlp,text,unsupervised
Classifier: Intended Audience :: Science/Research
Classifier: License :: OSI Approved :: MIT License
Classifier: Operating System :: OS Independent
Classifier: Programming Language :: Python :: 3
Classifier: Topic :: Scientific/Engineering :: Artificial Intelligence
Requires-Python: >=3.9
Requires-Dist: numpy>=1.24
Requires-Dist: pandas>=1.5
Requires-Dist: scikit-learn>=1.2
Requires-Dist: scipy>=1.10
Requires-Dist: torch>=2.0; platform_system != 'Darwin' or platform_machine != 'arm64'
Requires-Dist: tqdm>=4.66
Requires-Dist: transformers>=4.41
